video2gif/__init__.py
video2gif/main.py
video2gif-1.1.1.dist-info/LICENSE
video2gif-1.1.1.dist-info/METADATA
video2gif-1.1.1.dist-info/WHEEL
video2gif-1.1.1.dist-info/entry_points.txt
video2gif-1.1.1.dist-info/RECORD
